{
  "fr": {
    "strings": {
      "home.badge": "Banque mobile",
      "home.title": "Gardez le contrôle|de votre argent.",
      "home.cta": "Découvrir mes comptes",
      "home.legal": "Données de démonstration · the404squad",
      "acc.current": "Compte courant",
      "acc.income": "Revenus",
      "acc.expenses": "Dépenses",
      "acc.send": "Allouer à une catégorie",
      "acc.pay": "Simuler un paiement",
      "acc.where": "Où part votre argent",
      "acc.totalSpent": "Total dépensé",
      "acc.spent": "dépensé",
      "acc.left": "dispo",
      "acc.empty": "Aucun budget alloué",
      "acc.myCats": "Mes catégories",
      "acc.tapHint": "Touchez pour les détails",
      "acc.addCat": "Ajouter une catégorie",
      "acc.footer": "Vos données restent locales · the404squad pour ING",
      "acc.tabAccounts": "Comptes",
      "acc.tabHome": "Accueil",
      "acc.tabProfile": "Profil",
      "det.spentThisMonth": "Dépensé ce mois",
      "det.trend6": "Tendance sur 6 mois",
      "det.transactions": "Opérations",
      "det.empty": "Aucune opération ce mois-ci.",
      "det.ops": "op.",
      "det.alloc": "épargne / placement",
      "sheet.sendTitle": "Allouer de l'argent",
      "sheet.to": "Vers quelle catégorie",
      "sheet.amount": "Montant",
      "sheet.available": "Solde disponible",
      "sheet.sendCta": "Allouer",
      "sheet.errAmount": "Saisissez un montant valide.",
      "sheet.errFunds": "Solde insuffisant.",
      "sheet.errCat": "Choisissez une catégorie.",
      "sheet.sent": "Alloué à",
      "sheet.newCatTitle": "Nouvelle catégorie",
      "sheet.name": "Nom",
      "sheet.namePh": "Ex : Voyages",
      "sheet.icon": "Icône",
      "sheet.color": "Couleur",
      "sheet.budget": "Budget mensuel (optionnel)",
      "sheet.createCta": "Créer la catégorie",
      "sheet.errName": "Donnez un nom à la catégorie.",
      "sheet.created": "Catégorie créée",
      "sheet.saving": "Enregistrement…",
      "pay.title": "Simuler un paiement",
      "pay.merchant": "Marchand",
      "pay.merchantPh": "Ex : Uber Eats, Carrefour…",
      "pay.quick": "Marchands fréquents",
      "pay.note": "L'app range automatiquement la dépense dans la bonne catégorie.",
      "pay.cta": "Payer",
      "pay.errMerchant": "Indiquez un marchand.",
      "pay.done": "Payé",
      "pay.others": "Marchand non reconnu → rangé dans « Autres ».",
      "pay.fromEnv": "enveloppe",
      "pay.fromMain": "compte",
      "pay.allMain": "enveloppe vide → débité du compte",
      "menu.title": "Mon profil",
      "menu.settings": "Paramètres",
      "menu.language": "Langue",
      "menu.help": "Aide & support",
      "menu.security": "Sécurité",
      "menu.logout": "Déconnexion",
      "menu.age": "ans",
      "transfer.label": "Virement vers",
      "ai.title": "Projection IA",
      "ai.in1y": "Épargne estimée d'ici 1 an",
      "ai.now": "auj.",
      "ai.weekly": "Dépensé cette semaine",
      "ai.monthlySave": "Épargne / mois",
      "ai.lvlPositive": "Sur la bonne voie",
      "ai.lvlTight": "Marge serrée",
      "ai.lvlNegative": "Budget dépassé",
      "ai.insightPositive": "Au rythme de {week}/semaine, vous épargneriez {year} d'ici un an. Continuez comme ça !",
      "ai.insightTight": "Vous mettez {month}/mois de côté, soit {year} sur un an. Marge serrée : surveillez vos dépenses.",
      "ai.insightNegative": "À ce rythme, vos dépenses dépassent vos revenus de {over}/mois. Réduisez pour repasser dans le vert.",
      "err.load": "Erreur de chargement"
    },
    "slogans": [
      "Chaque euro compte.",
      "Vos finances, enfin lisibles.",
      "Dépensez malin, épargnez serein.",
      "Votre avenir se construit aujourd'hui."
    ],
    "features": [
      { "ic": "📊", "t": "Vos dépenses, en clair", "d": "Réparties par catégorie, en temps réel." },
      { "ic": "🎯", "t": "Des budgets qui vous parlent", "d": "Alertes dès que ça dérape." },
      { "ic": "🚀", "t": "Faites grandir votre épargne", "d": "Projetez votre patrimoine sur 10 ans." }
    ],
    "months": ["janvier","février","mars","avril","mai","juin","juillet","août","septembre","octobre","novembre","décembre"],
    "monthsShort": ["jan","fév","mar","avr","mai","juin","juil","aoû","sep","oct","nov","déc"]
  },
  "en": {
    "strings": {
      "home.badge": "Mobile banking",
      "home.title": "Stay in control|of your money.",
      "home.cta": "Explore my accounts",
      "home.legal": "Demo data · the404squad",
      "acc.current": "Current account",
      "acc.income": "Income",
      "acc.expenses": "Expenses",
      "acc.send": "Allocate to a category",
      "acc.pay": "Simulate a payment",
      "acc.where": "Where your money goes",
      "acc.totalSpent": "Total spent",
      "acc.spent": "spent",
      "acc.left": "left",
      "acc.empty": "No budget allocated",
      "acc.myCats": "My categories",
      "acc.tapHint": "Tap for details",
      "acc.addCat": "Add a category",
      "acc.footer": "Your data stays local · the404squad for ING",
      "acc.tabAccounts": "Accounts",
      "acc.tabHome": "Home",
      "acc.tabProfile": "Profile",
      "det.spentThisMonth": "Spent this month",
      "det.trend6": "6-month trend",
      "det.transactions": "Transactions",
      "det.empty": "No transactions this month.",
      "det.ops": "ops",
      "det.alloc": "savings / investment",
      "sheet.sendTitle": "Allocate money",
      "sheet.to": "To which category",
      "sheet.amount": "Amount",
      "sheet.available": "Available balance",
      "sheet.sendCta": "Allocate",
      "sheet.errAmount": "Enter a valid amount.",
      "sheet.errFunds": "Insufficient balance.",
      "sheet.errCat": "Pick a category.",
      "sheet.sent": "Allocated to",
      "sheet.newCatTitle": "New category",
      "sheet.name": "Name",
      "sheet.namePh": "e.g. Travel",
      "sheet.icon": "Icon",
      "sheet.color": "Color",
      "sheet.budget": "Monthly budget (optional)",
      "sheet.createCta": "Create category",
      "sheet.errName": "Give the category a name.",
      "sheet.created": "Category created",
      "sheet.saving": "Saving…",
      "pay.title": "Simulate a payment",
      "pay.merchant": "Merchant",
      "pay.merchantPh": "e.g. Uber Eats, Carrefour…",
      "pay.quick": "Frequent merchants",
      "pay.note": "The app files the expense in the right category automatically.",
      "pay.cta": "Pay",
      "pay.errMerchant": "Enter a merchant.",
      "pay.done": "Paid",
      "pay.others": "Merchant not recognized → filed under “Others”.",
      "pay.fromEnv": "envelope",
      "pay.fromMain": "main account",
      "pay.allMain": "empty envelope → charged to account",
      "menu.title": "My profile",
      "menu.settings": "Settings",
      "menu.language": "Language",
      "menu.help": "Help & support",
      "menu.security": "Security",
      "menu.logout": "Log out",
      "menu.age": "y.o.",
      "transfer.label": "Transfer to",
      "ai.title": "AI forecast",
      "ai.in1y": "Estimated savings in 1 year",
      "ai.now": "now",
      "ai.weekly": "Spent this week",
      "ai.monthlySave": "Savings / month",
      "ai.lvlPositive": "On track",
      "ai.lvlTight": "Tight margin",
      "ai.lvlNegative": "Over budget",
      "ai.insightPositive": "At {week}/week, you'd save {year} within a year. Keep it up!",
      "ai.insightTight": "You set aside {month}/month, i.e. {year} over a year. Tight margin: watch your spending.",
      "ai.insightNegative": "At this pace, your spending exceeds your income by {over}/month. Cut back to get back in the green.",
      "err.load": "Loading error"
    },
    "slogans": [
      "Every euro counts.",
      "Your finances, finally clear.",
      "Spend smart, save easy.",
      "Your future starts today."
    ],
    "features": [
      { "ic": "📊", "t": "Your spending, made clear", "d": "Split by category, in real time." },
      { "ic": "🎯", "t": "Budgets that talk to you", "d": "Alerts the moment you overspend." },
      { "ic": "🚀", "t": "Grow your savings", "d": "Project your wealth over 10 years." }
    ],
    "months": ["January","February","March","April","May","June","July","August","September","October","November","December"],
    "monthsShort": ["jan","feb","mar","apr","may","jun","jul","aug","sep","oct","nov","dec"]
  },
  "nl": {
    "strings": {
      "home.badge": "Mobiel bankieren",
      "home.title": "Hou grip|op je geld.",
      "home.cta": "Mijn rekeningen ontdekken",
      "home.legal": "Demogegevens · the404squad",
      "acc.current": "Zichtrekening",
      "acc.income": "Inkomsten",
      "acc.expenses": "Uitgaven",
      "acc.send": "Toewijzen aan een categorie",
      "acc.pay": "Een betaling simuleren",
      "acc.where": "Waar je geld naartoe gaat",
      "acc.totalSpent": "Totaal uitgegeven",
      "acc.spent": "uitgegeven",
      "acc.left": "beschikbaar",
      "acc.empty": "Geen budget toegewezen",
      "acc.myCats": "Mijn categorieën",
      "acc.tapHint": "Tik voor details",
      "acc.addCat": "Categorie toevoegen",
      "acc.footer": "Je gegevens blijven lokaal · the404squad voor ING",
      "acc.tabAccounts": "Rekeningen",
      "acc.tabHome": "Start",
      "acc.tabProfile": "Profiel",
      "det.spentThisMonth": "Deze maand uitgegeven",
      "det.trend6": "Trend over 6 maanden",
      "det.transactions": "Verrichtingen",
      "det.empty": "Geen verrichtingen deze maand.",
      "det.ops": "verr.",
      "det.alloc": "sparen / belegging",
      "sheet.sendTitle": "Geld toewijzen",
      "sheet.to": "Aan welke categorie",
      "sheet.amount": "Bedrag",
      "sheet.available": "Beschikbaar saldo",
      "sheet.sendCta": "Toewijzen",
      "sheet.errAmount": "Voer een geldig bedrag in.",
      "sheet.errFunds": "Onvoldoende saldo.",
      "sheet.errCat": "Kies een categorie.",
      "sheet.sent": "Toegewezen aan",
      "sheet.newCatTitle": "Nieuwe categorie",
      "sheet.name": "Naam",
      "sheet.namePh": "Bv. Reizen",
      "sheet.icon": "Icoon",
      "sheet.color": "Kleur",
      "sheet.budget": "Maandbudget (optioneel)",
      "sheet.createCta": "Categorie aanmaken",
      "sheet.errName": "Geef de categorie een naam.",
      "sheet.created": "Categorie aangemaakt",
      "sheet.saving": "Opslaan…",
      "pay.title": "Een betaling simuleren",
      "pay.merchant": "Handelaar",
      "pay.merchantPh": "Bv. Uber Eats, Carrefour…",
      "pay.quick": "Frequente handelaars",
      "pay.note": "De app plaatst de uitgave automatisch in de juiste categorie.",
      "pay.cta": "Betalen",
      "pay.errMerchant": "Geef een handelaar op.",
      "pay.done": "Betaald",
      "pay.others": "Handelaar niet herkend → geplaatst onder « Overige ».",
      "pay.fromEnv": "envelop",
      "pay.fromMain": "rekening",
      "pay.allMain": "envelop leeg → van rekening afgehaald",
      "menu.title": "Mijn profiel",
      "menu.settings": "Instellingen",
      "menu.language": "Taal",
      "menu.help": "Hulp & ondersteuning",
      "menu.security": "Beveiliging",
      "menu.logout": "Afmelden",
      "menu.age": "jaar",
      "transfer.label": "Overschrijving naar",
      "ai.title": "AI-prognose",
      "ai.in1y": "Geschat spaargeld over 1 jaar",
      "ai.now": "nu",
      "ai.weekly": "Deze week uitgegeven",
      "ai.monthlySave": "Sparen / maand",
      "ai.lvlPositive": "Op koers",
      "ai.lvlTight": "Krappe marge",
      "ai.lvlNegative": "Budget overschreden",
      "ai.insightPositive": "Aan {week}/week zou je {year} sparen binnen een jaar. Goed bezig!",
      "ai.insightTight": "Je legt {month}/maand opzij, oftewel {year} op een jaar. Krappe marge: let op je uitgaven.",
      "ai.insightNegative": "Aan dit tempo overschrijden je uitgaven je inkomsten met {over}/maand. Bespaar om weer in het groen te komen.",
      "err.load": "Laadfout"
    },
    "slogans": [
      "Elke euro telt.",
      "Je financiën, eindelijk helder.",
      "Slim uitgeven, zorgeloos sparen.",
      "Je toekomst bouw je vandaag."
    ],
    "features": [
      { "ic": "📊", "t": "Je uitgaven, helder", "d": "Per categorie, in real time." },
      { "ic": "🎯", "t": "Budgetten die meespreken", "d": "Meldingen zodra het ontspoort." },
      { "ic": "🚀", "t": "Laat je spaargeld groeien", "d": "Projecteer je vermogen over 10 jaar." }
    ],
    "months": ["januari","februari","maart","april","mei","juni","juli","augustus","september","oktober","november","december"],
    "monthsShort": ["jan","feb","mrt","apr","mei","jun","jul","aug","sep","okt","nov","dec"]
  }
}
